bigsuds.py
setup.cfg
setup.py
bigsuds_with_jork.egg-info/PKG-INFO
bigsuds_with_jork.egg-info/SOURCES.txt
bigsuds_with_jork.egg-info/dependency_links.txt
bigsuds_with_jork.egg-info/requires.txt
bigsuds_with_jork.egg-info/top_level.txt