Metadata-Version: 1.1
Name: bigsuds-with-jork
Version: 1.0.2
Summary: Library for F5 Networks iControl API. This fork uses jorks suds fork
Home-page: http://devcentral.f5.com
Author: F5 Networks, Inc.
Author-email: me@joaoubaldo.com
License: https://devcentral.f5.com/resources/devcentral-eula
Keywords: f5 icontrol
Platform: UNKNOWN
Classifier: Development Status :: 5 - Production/Stable
Classifier: Intended Audience :: Developers
Classifier: Programming Language :: Python :: 2
Classifier: Programming Language :: Python :: 2.4
Classifier: Programming Language :: Python :: 2.5
Classifier: Programming Language :: Python :: 2.6
Classifier: Programming Language :: Python :: 2.7
